youtubedataapisearch/__init__.py
youtubedataapisearch/api_helper.py
youtubedataapisearch/configuration.py
youtubedataapisearch/decorators.py
youtubedataapisearch/youtubedataapisearch_client.py
youtubedataapisearch/controllers/__init__.py
youtubedataapisearch/controllers/base_controller.py
youtubedataapisearch/controllers/simple_search_controller.py
youtubedataapisearch/exceptions/__init__.py
youtubedataapisearch/exceptions/api_exception.py
youtubedataapisearch/exceptions/invalid_argument_exception.py
youtubedataapisearch/exceptions/invalid_video_id_exception.py
youtubedataapisearch/http/__init__.py
youtubedataapisearch/http/http_call_back.py
youtubedataapisearch/http/http_client.py
youtubedataapisearch/http/http_method_enum.py
youtubedataapisearch/http/http_request.py
youtubedataapisearch/http/http_response.py
youtubedataapisearch/http/requests_client.py
youtubedataapisearch/models/__init__.py
youtubedataapisearch/models/type_search_enum.py
youtubedataapisearch/utilities/__init__.py
youtubedataapisearch/utilities/file_wrapper.py
youtube_data_py-1.0.dist-info/LICENSE
youtube_data_py-1.0.dist-info/METADATA
youtube_data_py-1.0.dist-info/WHEEL
youtube_data_py-1.0.dist-info/top_level.txt
youtube_data_py-1.0.dist-info/RECORD
